datadog_cdk_constructs/__init__.py
datadog_cdk_constructs/py.typed
datadog_cdk_constructs/_jsii/__init__.py
datadog_cdk_constructs/_jsii/datadog-cdk-constructs@0.9.1.jsii.tgz
datadog_cdk_constructs-0.9.1.dist-info/LICENSE
datadog_cdk_constructs-0.9.1.dist-info/METADATA
datadog_cdk_constructs-0.9.1.dist-info/WHEEL
datadog_cdk_constructs-0.9.1.dist-info/top_level.txt
datadog_cdk_constructs-0.9.1.dist-info/RECORD
