Metadata-Version: 2.1
Name: datadog-cdk-constructs
Version: 0.9.1
Summary: CDK Construct Library to automatically instrument Python and Node Lambda functions with Datadog
Home-page: https://github.com/DataDog/datadog-cdk-constructs
Author: Datadog
License: Apache-2.0
Project-URL: Source, https://github.com/DataDog/datadog-cdk-constructs
Platform: UNKNOWN
Classifier: Intended Audience :: Developers
Classifier: Operating System :: OS Independent
Classifier: Programming Language :: JavaScript
Classifier: Programming Language :: Python :: 3 :: Only
Classifier: Programming Language :: Python :: 3.6
Classifier: Programming Language :: Python :: 3.7
Classifier: Programming Language :: Python :: 3.8
Classifier: Programming Language :: Python :: 3.9
Classifier: Typing :: Typed
Classifier: Development Status :: 5 - Production/Stable
Classifier: License :: OSI Approved
Requires-Python: >=3.6
License-File: LICENSE
Requires-Dist: aws-cdk.aws-apigateway (<2.0.0,>=1.134.0)
Requires-Dist: aws-cdk.aws-lambda-nodejs (<2.0.0,>=1.134.0)
Requires-Dist: aws-cdk.aws-lambda-python (<2.0.0,>=1.134.0)
Requires-Dist: aws-cdk.aws-lambda (<2.0.0,>=1.134.0)
Requires-Dist: aws-cdk.aws-logs-destinations (<2.0.0,>=1.134.0)
Requires-Dist: aws-cdk.aws-logs (<2.0.0,>=1.134.0)
Requires-Dist: aws-cdk.core (<2.0.0,>=1.134.0)
Requires-Dist: constructs (<4.0.0,>=3.2.27)
Requires-Dist: jsii (<2.0.0,>=1.46.0)
Requires-Dist: publication (>=0.0.3)
